electricity_network_file_parser/FileParser.py
electricity_network_file_parser/GnfParser.py
electricity_network_file_parser/__init__.py
electricity_network_file_parser/dataclasses.py
electricity_network_file_parser-0.0.3.dist-info/METADATA
electricity_network_file_parser-0.0.3.dist-info/WHEEL
electricity_network_file_parser-0.0.3.dist-info/licenses/LICENSE
electricity_network_file_parser-0.0.3.dist-info/RECORD
