Metadata-Version: 2.4
Name: electricity_network_file_parser
Version: 0.0.3
Summary: A Python package for parsing gaia and vision files. 
Project-URL: Homepage, https://github.com/EES-TUe/network-file-parser
Project-URL: Issues, https://github.com/EES-TUe/network-file-parser/issues
Author-email: Leo van Schooten <l.g.t.v.schooten@tue.nl>
License-File: LICENSE
Classifier: License :: OSI Approved :: MIT License
Classifier: Operating System :: OS Independent
Classifier: Programming Language :: Python :: 3
Requires-Python: >=3.8
Requires-Dist: openpyxl==3.1.5
Requires-Dist: pandas==2.2.3
